{
  "lastUpdate": "2025-12-20T06:23:15.317Z",
  "day": "Måndag",
  "menus": [
    {
      "restaurant": "Partymakarna",
      "location": "Slakthusområdet, Stockholm",
      "menu": "(Visar måndagens meny)\n\n• Stekt torskfilé med dill och romsås, kokt potatis och varma grönsaker\n• Våra goda köttbullar med kantarellsås, Lingonsylt och kokt potatis\n• Syrliga isterband med persiljestuvad potatis och rödbetor\n• Veg: kikärtsbiff med kantarellsås och varma grönsaker\n• Grekisk fetaostsallad med kalamataoliver och picklad lök",
      "status": "success"
    }
  ]
}