{
  "lastUpdate": "2026-03-26T07:01:32.348Z",
  "day": "Torsdag",
  "menus": [
    {
      "restaurant": "Partymakarna",
      "location": "Slakthusområdet, Stockholm",
      "menu": "• Ärtsoppa med eller utan fläsk, pannkaka med sylt och grädde\n• Viltköttbullar med skogssvampsås, potatismos och svartvinbärsgelé\n• Fiskgratäng med skaldjurssås, potatismos och fänkålssallad\n• Vegetarisk kikärtsbiff med skogssvamp, potatismos och örtaioli\n• Stor portion pannkaka med sylt och grädde\n• Sallad med varmrökt lax, färskpotatissallad och senapscrème",
      "status": "success"
    }
  ]
}